CHANGES.txt
CONTRIBUTORS.txt
MANIFEST.in
README.txt
setup.py
collective/__init__.py
collective.kupuemoticons.egg-info/PKG-INFO
collective.kupuemoticons.egg-info/SOURCES.txt
collective.kupuemoticons.egg-info/dependency_links.txt
collective.kupuemoticons.egg-info/namespace_packages.txt
collective.kupuemoticons.egg-info/not-zip-safe
collective.kupuemoticons.egg-info/requires.txt
collective.kupuemoticons.egg-info/top_level.txt
collective/kupuemoticons/CHANGELOG
collective/kupuemoticons/__init__.py
collective/kupuemoticons/configure.zcml
collective/kupuemoticons/profiles.zcml
collective/kupuemoticons/setuphandlers.py
collective/kupuemoticons/skins.zcml
collective/kupuemoticons/version.txt
collective/kupuemoticons/browser/__init__.py
collective/kupuemoticons/browser/configure.zcml
collective/kupuemoticons/browser/interfaces.py
collective/kupuemoticons/browser/scripts/initcustomtools.js
collective/kupuemoticons/browser/scripts/kuputools.js
collective/kupuemoticons/browser/stylesheets/kupustyles.css
collective/kupuemoticons/browser/stylesheets/kuputools.kss
collective/kupuemoticons/profiles/default/collective.kupuemoticons_various.txt
collective/kupuemoticons/profiles/default/cssregistry.xml
collective/kupuemoticons/profiles/default/import_steps.xml
collective/kupuemoticons/profiles/default/jsregistry.xml
collective/kupuemoticons/profiles/default/kssregistry.xml
collective/kupuemoticons/profiles/default/metadata.xml
collective/kupuemoticons/profiles/default/skins.xml
collective/kupuemoticons/skins/collective_kupuemoticons_custom_images/CONTENT.txt
collective/kupuemoticons/skins/collective_kupuemoticons_custom_images/smiley_angry.gif
collective/kupuemoticons/skins/collective_kupuemoticons_custom_images/smiley_bored.gif
collective/kupuemoticons/skins/collective_kupuemoticons_custom_images/smiley_cool.gif
collective/kupuemoticons/skins/collective_kupuemoticons_custom_images/smiley_curious.gif
collective/kupuemoticons/skins/collective_kupuemoticons_custom_images/smiley_dead.gif
collective/kupuemoticons/skins/collective_kupuemoticons_custom_images/smiley_doh.gif
collective/kupuemoticons/skins/collective_kupuemoticons_custom_images/smiley_grin.gif
collective/kupuemoticons/skins/collective_kupuemoticons_custom_images/smiley_josh.gif
