Metadata-Version: 1.0
Name: collective.kupuemoticons
Version: 0.0.3
Summary: UNKNOWN
Home-page: http://svn.plone.org/svn/collective/collective.kupuemoticons/tags/0.0.3
Author: Ramon Bartl
Author-email: ramon.bartl@inquant.de
License: GPL
Keywords: kupu plone zope emoticons
Platform: UNKNOWN
Classifier: Framework :: Plone
Classifier: Intended Audience :: Developers
Classifier: Topic :: Software Development :: Libraries :: Python Modules
Classifier: License :: OSI Approved :: GNU General Public License (GPL)
